nicou11_lotto/__init__.py
nicou11_lotto/draw.py
nicou11_lotto-0.2.0.dist-info/METADATA
nicou11_lotto-0.2.0.dist-info/WHEEL
nicou11_lotto-0.2.0.dist-info/top_level.txt
nicou11_lotto-0.2.0.dist-info/RECORD
