Metadata-Version: 2.1
Name: nicou11_lotto
Version: 0.2.0
Summary: Default template for PDM package
Author-email: Nicou11 <lyoungin1204@gmail.com>
License: MIT
Requires-Python: >=3.9
